aliyah_sdk/__init__.py
aliyah_sdk/__version__.py
aliyah_sdk/config.py
aliyah_sdk/exceptions.py
aliyah_sdk/client/__init__.py
aliyah_sdk/client/client.py
aliyah_sdk/client/api/__init__.py
aliyah_sdk/client/api/base.py
aliyah_sdk/client/api/types.py
aliyah_sdk/client/api/versions/__init__.py
aliyah_sdk/client/api/versions/v1.py
aliyah_sdk/client/http/__init__.py
aliyah_sdk/client/http/http_adapter.py
aliyah_sdk/client/http/http_client.py
aliyah_sdk/helpers/__init__.py
aliyah_sdk/helpers/dashboard.py
aliyah_sdk/helpers/debug.py
aliyah_sdk/helpers/env.py
aliyah_sdk/helpers/serialization.py
aliyah_sdk/helpers/system.py
aliyah_sdk/helpers/time.py
aliyah_sdk/helpers/validation.py
aliyah_sdk/helpers/version.py
aliyah_sdk/instrumentation/__init__.py
aliyah_sdk/instrumentation/anthropic/__init__.py
aliyah_sdk/instrumentation/anthropic/event_handler_wrapper.py
aliyah_sdk/instrumentation/anthropic/instrumentor.py
aliyah_sdk/instrumentation/anthropic/stream_wrapper.py
aliyah_sdk/instrumentation/anthropic/attributes/__init__.py
aliyah_sdk/instrumentation/anthropic/attributes/common.py
aliyah_sdk/instrumentation/anthropic/attributes/message.py
aliyah_sdk/instrumentation/anthropic/attributes/tools.py
aliyah_sdk/instrumentation/common/__init__.py
aliyah_sdk/instrumentation/common/attributes.py
aliyah_sdk/instrumentation/common/objects.py
aliyah_sdk/instrumentation/common/wrappers.py
aliyah_sdk/instrumentation/crewai/__init__.py
aliyah_sdk/instrumentation/crewai/crewai_span_attributes.py
aliyah_sdk/instrumentation/crewai/instrumentation.py
aliyah_sdk/instrumentation/crewai/version.py
aliyah_sdk/instrumentation/google_generativeai/__init__.py
aliyah_sdk/instrumentation/google_generativeai/instrumentor.py
aliyah_sdk/instrumentation/google_generativeai/stream_wrapper.py
aliyah_sdk/instrumentation/google_generativeai/attributes/__init__.py
aliyah_sdk/instrumentation/google_generativeai/attributes/chat.py
aliyah_sdk/instrumentation/google_generativeai/attributes/common.py
aliyah_sdk-0.1.5.dist-info/licenses/LICENSE
aliyah_sdk-0.1.5.dist-info/METADATA
aliyah_sdk-0.1.5.dist-info/WHEEL
aliyah_sdk-0.1.5.dist-info/top_level.txt
aliyah_sdk-0.1.5.dist-info/RECORD
