Metadata-Version: 2.4
Name: aliyah-sdk
Version: 0.1.5
Summary: Aaliyah SDK for connecting AI agents to the Mensterra platform for compliance checking and monitoring.
Author-email: Mensterra <support@mensterra.com>
License:                                  Apache License
Keywords: ai,agent,monitoring,compliance,governance,opentelemetry
Classifier: Programming Language :: Python :: 3
Classifier: License :: OSI Approved :: Apache Software License
Classifier: Operating System :: OS Independent
Classifier: Intended Audience :: Developers
Classifier: Topic :: Scientific/Engineering :: Artificial Intelligence
Classifier: Topic :: Software Development :: Libraries :: Python Modules
Classifier: Topic :: System :: Monitoring
Requires-Python: >=3.10
License-File: LICENSE
Requires-Dist: requests
Requires-Dist: wrapt
Requires-Dist: psutil
Requires-Dist: termcolor
Requires-Dist: opentelemetry-api<1.34.0,>=1.33.0
Requires-Dist: opentelemetry-sdk<1.34.0,>=1.33.0
Requires-Dist: opentelemetry-instrumentation<0.55b0,>=0.54b0
Requires-Dist: opentelemetry-semantic-conventions<0.55b0,>=0.54b0
Requires-Dist: opentelemetry-exporter-otlp-proto-http<1.34.0,>=1.33.0
Requires-Dist: opentelemetry-instrumentation-openai
Requires-Dist: opentelemetry-instrumentation-anthropic
Requires-Dist: opentelemetry-instrumentation-google-generativeai
Requires-Dist: pydantic
Requires-Dist: typing-extensions
Requires-Dist: python-dotenv
Requires-Dist: PyYAML
Requires-Dist: openai
Requires-Dist: anthropic
Requires-Dist: google-generativeai
Requires-Dist: karo
Requires-Dist: openpyxl
Requires-Dist: pandas
Requires-Dist: jsonpatch
Requires-Dist: jsonpointer
Requires-Dist: jsonschema
Requires-Dist: referencing
Requires-Dist: rpds-py
Requires-Dist: websocket-client
Requires-Dist: websockets
Requires-Dist: watchfiles
Provides-Extra: all-llm
Requires-Dist: opentelemetry-instrumentation-openai; extra == "all-llm"
Requires-Dist: opentelemetry-instrumentation-anthropic; extra == "all-llm"
Requires-Dist: opentelemetry-instrumentation-google-generativeai; extra == "all-llm"
Requires-Dist: opentelemetry-instrumentation-bedrock; extra == "all-llm"
Requires-Dist: opentelemetry-instrumentation-cohere; extra == "all-llm"
Requires-Dist: opentelemetry-instrumentation-langchain; extra == "all-llm"
Requires-Dist: opentelemetry-instrumentation-llamaindex; extra == "all-llm"
Provides-Extra: openai
Requires-Dist: opentelemetry-instrumentation-openai; extra == "openai"
Provides-Extra: anthropic
Requires-Dist: opentelemetry-instrumentation-anthropic; extra == "anthropic"
Provides-Extra: google
Requires-Dist: opentelemetry-instrumentation-google-generativeai; extra == "google"
Provides-Extra: aws
Requires-Dist: opentelemetry-instrumentation-bedrock; extra == "aws"
Provides-Extra: cohere
Requires-Dist: opentelemetry-instrumentation-cohere; extra == "cohere"
Provides-Extra: frameworks
Requires-Dist: opentelemetry-instrumentation-langchain; extra == "frameworks"
Requires-Dist: opentelemetry-instrumentation-llamaindex; extra == "frameworks"
Provides-Extra: dev
Requires-Dist: pytest; extra == "dev"
Requires-Dist: pytest-cov; extra == "dev"
Requires-Dist: black; extra == "dev"
Requires-Dist: isort; extra == "dev"
Requires-Dist: mypy; extra == "dev"
Requires-Dist: pre-commit; extra == "dev"
Dynamic: license-file
